metta/__init__.py
metta/common/__init__.py
metta/common/config.py
metta/common/shared_memory.py
metta/common/time_utils.py
metta/common/zmq.py
metta/processors/__init__.py
metta/processors/audio/__init__.py
metta/processors/audio/url_audio_source.py
metta/processors/base_processor.py
metta/processors/edge_processor.py
metta/processors/sink_processor.py
metta/processors/source_processor.py
metta/processors/video/__init__.py
metta/processors/video/display_sink.py
metta/processors/video/video_source.py
metta/topics/__init__.py
metta/topics/topic_registry.py
metta/topics/topics.py
metta/types/__init__py
metta/types/dtype_pb2.py
metta/types/dtype_pb2.pyi
metta/types/ndarray_pb2.py
metta/types/ndarray_pb2.pyi
metta/types/plasma_pb2.py
metta/types/plasma_pb2.pyi
metta/types/topic_pb2.py
metta/types/topic_pb2.pyi
metta-2.1.0.dist-info/LICENSE
metta-2.1.0.dist-info/WHEEL
metta-2.1.0.dist-info/METADATA
metta-2.1.0.dist-info/RECORD
